[
    {
        "COMPANY": "KOBSA",
        "LINK": "https://magnavoz-us.digitalkcloud.com/Reporting/BIReports/cdrs.html#Atoday:now/-300/asig_carrier_group=cc%20Kobsa%20Prepago/aga:bgDbeGmeG2h7OdZWdB/Untitled%20report//kobsa%20report%20x%20day",
        "LINK_D":"https://magnavoz-us.digitalkcloud.com/Reporting/BIReports/cdrs.html#A2022-01-07%2000%3A00%3A00:2022-01-07%2023%3A59%3A59/-300/asig_carrier_group=cc%20Kobsa%20Prepago",
        "FILTER": "81,26,29,30,32,33,34,37,38,16,17,18,49",
        "FTP_FOLDER_MAIN":"/Kobsa-IN",
        "FTP_CN":{
            "host": "sftp.grupokobsa.com.pe",
            "port": 22,
            "username": "magnavoz",  
            "password": "L7jdby7-8KJF{"
        }

    },
    {
        "COMPANY": "RECSA",
        "LINK": "https://magnavoz-us.digitalkcloud.com/Reporting/BiReports/cdrs.html#A1%20month:1st/0/asig_carrier_group=Cc%20RECSA;asig_invite_status=200/aga:bgvbeDmeD2h7Od4WdB/Untitled%20report/dc:840",
        "FILTER": "26,29,30,32,33,34,37,38,16,17,18,49",
        "FTP_FOLDER_MAIN": "/uploads/CDRS",
        "FTP_CN":{
            "host": "161.132.172.170",            
            "port": 22,
            "username": "recsa",
            "password": "r3cs4.."
        }
    },
    {
        "COMPANY": "HDC",
        "LINK": "https://magnavoz-us.digitalkcloud.com/Reporting/BiReports/cdrs.html#Atoday:now/-300/asig_carrier_group=cc%20HDC/aja:bgLbeDcjldeThgvLdv2h7zoeiOd4/dc:840/cdr%20ayer%20HDC-%20para%20BOT%20automatico",
        "LINK_D":"https://magnavoz-us.digitalkcloud.com/Reporting/BIReports/cdrs.html#A2022-01-07%2000%3A00%3A00:2022-01-07%2023%3A59%3A59/-300/asig_carrier_group=cc%20Kobsa%20Prepago",
        "FILTER": "26,29,30,32,33,34,37,38,16,17,18,49",
        "FTP_FOLDER_MAIN":"/magnavoz",
        "FTP_CN":{
            "host": "sftp.hdec.pe",
            "port": 9122,
            "username": "user_magnavoz",  
            "password": "Us3r_M4gn4v0z%"
        }

    }
]